README.md
setup.py
augustine/__init__.py
augustine/_core.py
augustine/_logging_utilities.py
augustine/argument_processor.py
augustine/callable_argument_processor.py
augustine/command.py
augustine/command_argument_processor.py
augustine/command_line.py
augustine/command_line_app.py
augustine/create_basic_argument_parser.py
augustine/ensure_exists.py
augustine/environment_overlay.py
augustine/extra_feature.py
augustine/find_executable.py
augustine/find_module_definition.py
augustine/invoke_command.py
augustine/lazy_value.py
augustine/package_metadata.py
augustine/print_command_results.py
augustine/protected_run_command.py
augustine/remove_directory.py
augustine/run_command.py
augustine/simple_command_line_app.py
augustine/this_package_metadata.py
augustine/virtualenv_python.py
augustine.egg-info/PKG-INFO
augustine.egg-info/SOURCES.txt
augustine.egg-info/dependency_links.txt
augustine.egg-info/requires.txt
augustine.egg-info/top_level.txt
augustine/data/PACKAGE_NAME